README.md
_VERSION
files_com-1.6.283.dist-info/licenses/LICENSE
files_sdk/__init__.py
files_sdk/api.py
files_sdk/api_client.py
files_sdk/error.py
files_sdk/list_obj.py
files_sdk/path_util.py
files_sdk/util.py
files_sdk/models/__init__.py
files_sdk/models/account_line_item.py
files_sdk/models/action.py
files_sdk/models/action_notification_export.py
files_sdk/models/action_notification_export_result.py
files_sdk/models/agent_push_update.py
files_sdk/models/api_key.py
files_sdk/models/api_request_log.py
files_sdk/models/app.py
files_sdk/models/as2_incoming_message.py
files_sdk/models/as2_outgoing_message.py
files_sdk/models/as2_partner.py
files_sdk/models/as2_station.py
files_sdk/models/auto.py
files_sdk/models/automation.py
files_sdk/models/automation_log.py
files_sdk/models/automation_run.py
files_sdk/models/bandwidth_snapshot.py
files_sdk/models/behavior.py
files_sdk/models/bundle.py
files_sdk/models/bundle_action.py
files_sdk/models/bundle_download.py
files_sdk/models/bundle_notification.py
files_sdk/models/bundle_path.py
files_sdk/models/bundle_recipient.py
files_sdk/models/bundle_registration.py
files_sdk/models/child_site_management_policy.py
files_sdk/models/clickwrap.py
files_sdk/models/dns_record.py
files_sdk/models/email_incoming_message.py
files_sdk/models/email_log.py
files_sdk/models/errors.py
files_sdk/models/exavault_api_request_log.py
files_sdk/models/external_event.py
files_sdk/models/file.py
files_sdk/models/file_action.py
files_sdk/models/file_comment.py
files_sdk/models/file_comment_reaction.py
files_sdk/models/file_migration.py
files_sdk/models/file_migration_log.py
files_sdk/models/file_upload_part.py
files_sdk/models/folder.py
files_sdk/models/form_field.py
files_sdk/models/form_field_set.py
files_sdk/models/ftp_action_log.py
files_sdk/models/gpg_key.py
files_sdk/models/group.py
files_sdk/models/group_user.py
files_sdk/models/history.py
files_sdk/models/history_export.py
files_sdk/models/history_export_result.py
files_sdk/models/holiday_region.py
files_sdk/models/image.py
files_com-1.6.283.dist-info/METADATA
files_com-1.6.283.dist-info/WHEEL
files_com-1.6.283.dist-info/top_level.txt
files_com-1.6.283.dist-info/RECORD
