Metadata-Version: 2.4
Name: files_com
Version: 1.6.283
Summary: Python bindings for the Files.com API
License: MIT
Requires-Python: >=3.5
License-File: LICENSE
Requires-Dist: requests>=2.20
Requires-Dist: requests-toolbelt>=1.0.0
Dynamic: license-file
